django_admin_geomap/__init__.py
django_admin_geomap/templates/geomap/add_form.html
django_admin_geomap/templates/geomap/change_form.html
django_admin_geomap/templates/geomap/changelist.html
django_admin_geomap/templates/geomap/common.html
django_admin_geomap/templates/geomap/osm/add.html
django_admin_geomap/templates/geomap/osm/base.html
django_admin_geomap/templates/geomap/osm/drag.html
django_admin_geomap/templates/geomap/osm/popup.html
django_admin_geomap-1.6.dist-info/LICENSE
django_admin_geomap-1.6.dist-info/METADATA
django_admin_geomap-1.6.dist-info/WHEEL
django_admin_geomap-1.6.dist-info/top_level.txt
django_admin_geomap-1.6.dist-info/RECORD
