Metadata-Version: 2.1
Name: django-admin-geomap
Version: 1.6
Summary: Displaying objects at the maps in the Django views and administration site.
Home-page: https://github.com/vb64/django.admin.geomap
Author: Vitaly Bogomolov
Author-email: mail@vitaly-bogomolov.ru
Project-URL: Bug Tracker, https://github.com/vb64/django.admin.geomap/issues
Classifier: Programming Language :: Python :: 3
Classifier: License :: OSI Approved :: MIT License
Classifier: Operating System :: OS Independent
Requires-Python: >=3.6
License-File: LICENSE
